fcid/run.py
fcid/test_fcid.py
fcid-0.1.0.dist-info/licenses/LICENSE
fcid-0.1.0.dist-info/licenses/LICENSE.md
fcid-0.1.0.dist-info/METADATA
fcid-0.1.0.dist-info/WHEEL
fcid-0.1.0.dist-info/entry_points.txt
fcid-0.1.0.dist-info/top_level.txt
fcid-0.1.0.dist-info/RECORD
