Metadata-Version: 2.4
Name: fcid
Version: 0.1.0
Summary: Get Illumina sequencer metadata from flowcell/machine identifier
Author-email: Nick Waters <nickp60@gmail.com>
Maintainer-email: Nick Waters <nickp60@gmail.com>, Grammatikati Konstantin <stikus@mail.ru>
License: MIT
Classifier: Programming Language :: Python :: 3
Requires-Python: >=3.7
License-File: LICENSE
License-File: LICENSE.md
Dynamic: license-file
